tacopy/__init__.py
tacopy/py.typed
tacopy/transformer.py
tacopy/unparser.py
tacopy/validator.py
tacopy_optimization-0.1.3.dist-info/METADATA
tacopy_optimization-0.1.3.dist-info/WHEEL
tacopy_optimization-0.1.3.dist-info/licenses/LICENSE
tacopy_optimization-0.1.3.dist-info/RECORD
