Metadata-Version: 2.4
Name: tacopy-optimization
Version: 0.1.3
Summary: Tail-call optimization decorator for Python - eliminates recursion limits by transforming tail-recursive functions into iterative loops
Project-URL: Homepage, https://github.com/raaidrt/tacopy
Project-URL: Repository, https://github.com/raaidrt/tacopy
Project-URL: Issues, https://github.com/raaidrt/tacopy/issues
Project-URL: Documentation, https://github.com/raaidrt/tacopy/blob/main/README.md
Author-email: Raaid Tanveer <raaidraiyantanveer@gmail.com>
License: GPL-3.0-or-later
License-File: LICENSE
Keywords: ast,decorator,functional-programming,recursion,tail-call-optimization
Classifier: Development Status :: 3 - Alpha
Classifier: Intended Audience :: Developers
Classifier: License :: OSI Approved :: GNU General Public License v3 or later (GPLv3+)
Classifier: Programming Language :: Python :: 3
Classifier: Programming Language :: Python :: 3.10
Classifier: Programming Language :: Python :: 3.11
Classifier: Programming Language :: Python :: 3.12
Classifier: Programming Language :: Python :: 3.13
Classifier: Topic :: Software Development :: Code Generators
Classifier: Topic :: Software Development :: Libraries :: Python Modules
Classifier: Typing :: Typed
Requires-Python: >=3.10
Requires-Dist: astpretty>=3.0.0
Requires-Dist: tqdm>=4.67.1
